[
    {
        "name": "id",
        "dbType": "increments",
        "htmlType": "",
        "validations": "",
        "searchable": false,
        "fillable": false,
        "primary": true,
        "inForm": false,
        "inIndex": false
    },
    {
        "name": "duties",
        "dbType": "text",
        "htmlType": "textarea",
        "validations": "required",
        "searchable": true
    },
    {
        "name": "assignments",
        "dbType": "text",
        "htmlType": "textarea",
        "validations": "required",
        "searchable": true
    },
    {
        "name": "best_performance",
        "dbType": "string",
        "htmlType": "text",
        "validations": "required",
        "searchable": true
    },
    {
        "name": "uncomfortable",
        "dbType": "string",
        "htmlType": "text",
        "searchable": true
    },
    {
        "name": "opinion",
        "dbType": "string",
        "htmlType": "text",
        "validations": "required",
        "searchable": true
    },
    {
        "name": "contributions",
        "dbType": "text",
        "htmlType": "textarea",
        "validations": "required",
        "searchable": true
    },
    {
        "name": "community_engagement",
        "dbType": "string",
        "htmlType": "text",
        "validations": "required",
        "searchable": true
    },
    {
        "name": "comments",
        "dbType": "text",
        "htmlType": "textarea",
        "validations": "required",
        "searchable": true
    },
    {
        "name": "training",
        "dbType": "string",
        "htmlType": "text",
        "validations": "required",
        "searchable": true
    },
   {
		"name": "selfrating",
        "dbType": "integer",
        "htmlType": "radio,Outstanding:5,Commendable:4,Satisfactory:3,Needs-Improvement:2,Unsatisfactory:1"
   },
   {
    "name": "user_id",
    "dbType": "integer:unsigned:default,0:foreign,users,id",
    "htmlType": "text",
    "relation": "mt1,User,user_id,id"
},
{
    "type": "relation",
    "relation": "1tm,Comment"
},
{
    "name": "users",
    "type": "relation",
    "relation": "mtm,Role,user_roles,user_id,role_id"
},
{
    "name": "created_at",
    "dbType": "timestamp",
    "htmlType": "",
    "validations": "",
    "searchable": false,
    "fillable": false,
    "primary": false,
    "inForm": false,
    "inIndex": false
},
{
    "name": "updated_at",
    "dbType": "timestamp",
    "htmlType": "",
    "validations": "",
    "searchable": false,
    "fillable": false,
    "primary": false,
    "inForm": false,
    "inIndex": false
}
]